chemfunc/__about__.py
chemfunc/__init__.py
chemfunc/canonicalize_smiles.py
chemfunc/chemical_diversity.py
chemfunc/cluster_molecules.py
chemfunc/compute_properties.py
chemfunc/constants.py
chemfunc/convert_sdf.py
chemfunc/deduplicate_smiles.py
chemfunc/filter_molecules.py
chemfunc/main.py
chemfunc/measure_experimental_reproducibility.py
chemfunc/molecular_fingerprints.py
chemfunc/molecular_properties.py
chemfunc/molecular_similarities.py
chemfunc/nearest_neighbor.py
chemfunc/plot_property_distribution.py
chemfunc/plot_tsne.py
chemfunc/py.typed
chemfunc/regression_to_classification.py
chemfunc/sample_molecules.py
chemfunc/sdf_to_smarts.py
chemfunc/sdf_to_smiles.py
chemfunc/select_from_clusters.py
chemfunc/smiles_to_svg.py
chemfunc/visualize_molecules.py
chemfunc/visualize_reactions.py
chemfunc-1.0.12.dist-info/METADATA
chemfunc-1.0.12.dist-info/WHEEL
chemfunc-1.0.12.dist-info/entry_points.txt
chemfunc-1.0.12.dist-info/licenses/LICENSE.txt
chemfunc-1.0.12.dist-info/RECORD
