Metadata-Version: 2.4
Name: chemfunc
Version: 1.0.12
Summary: Useful functions and scripts for working with small molecules.
Project-URL: Homepage, https://github.com/swansonk14/chemfunc
Project-URL: Issues, https://github.com/swansonk14/chemfunc/issues
Author-email: Kyle Swanson <swansonk.14@gmail.com>
Maintainer-email: Kyle Swanson <swansonk.14@gmail.com>
License-Expression: MIT
License-File: LICENSE.txt
Keywords: computational chemistry
Classifier: License :: OSI Approved :: MIT License
Classifier: Operating System :: OS Independent
Classifier: Programming Language :: Python :: 3
Classifier: Programming Language :: Python :: 3.10
Classifier: Programming Language :: Python :: 3.11
Classifier: Programming Language :: Python :: 3.12
Classifier: Programming Language :: Python :: 3.13
Classifier: Typing :: Typed
Requires-Python: >=3.10
Requires-Dist: descriptastorus>=2.7.0.5
Requires-Dist: matplotlib
Requires-Dist: numpy
Requires-Dist: pandas
Requires-Dist: rdkit
Requires-Dist: scikit-learn
Requires-Dist: tqdm>=4.66.3
Requires-Dist: typed-argument-parser>=1.10.1
